pyturn/__init__.py
pyturn/stun_client.py
pyturn/turn_client.py
tests/__init__.py
tests/test_launcher.py
tests/test_stun_client.py
tests/test_turn_client.py
pyturn-0.2.4.1.dist-info/METADATA
pyturn-0.2.4.1.dist-info/WHEEL
pyturn-0.2.4.1.dist-info/top_level.txt
pyturn-0.2.4.1.dist-info/RECORD
